subroll/__init__.py
subroll/main.py
subroll-0.0.2.dist-info/LICENSE
subroll-0.0.2.dist-info/METADATA
subroll-0.0.2.dist-info/WHEEL
subroll-0.0.2.dist-info/top_level.txt
subroll-0.0.2.dist-info/RECORD
