Metadata-Version: 2.1
Name: subroll
Version: 0.0.2
Summary: Automatically choose a random IPv6 address from your subnet.
Home-page: https://github.com/witer33/subroll
Author: witer33
Author-email: dev@witer33.com
License: UNKNOWN
Project-URL: Bug Tracker, https://github.com/witer33/subroll/issues
Platform: UNKNOWN
Classifier: Programming Language :: Python :: 3
Classifier: License :: OSI Approved :: GNU General Public License v3 (GPLv3)
Classifier: Operating System :: OS Independent
Requires-Python: >=3.6
License-File: LICENSE
